[
  {
    "path": "posts/2019-10-27-arboles/",
    "title": "Arboles de Decisión",
    "description": "A short description of the post.",
    "author": [
      {
        "name": "Gabriel Cabrera",
        "url": {}
      }
    ],
    "date": "2019-10-27",
    "categories": [],
    "preview": {},
    "last_modified": "2019-10-27T17:56:12-03:00"
  },
  {
    "path": "posts/2019-10-27-entropy/",
    "title": "Entropía en Machine Learning",
    "description": "A short description of the post.",
    "author": [
      {
        "name": "Gabriel Cabrera",
        "url": {}
      }
    ],
    "date": "2019-10-27",
    "categories": [],
    "preview": {},
    "last_modified": "2019-10-27T17:51:46-03:00"
  },
  {
    "path": "posts/2019-10-27-jupyter/",
    "title": "Jupyter Notebooks",
    "description": "A short description of the post.",
    "author": [
      {
        "name": "Gabriel Cabrera",
        "url": {}
      }
    ],
    "date": "2019-10-27",
    "categories": [],
    "preview": {},
    "last_modified": "2019-10-27T17:51:55-03:00"
  },
  {
    "path": "posts/2019-10-27-random/",
    "title": "Random Forest",
    "description": "A short description of the post.",
    "author": [
      {
        "name": "Gabriel Cabrera",
        "url": {}
      }
    ],
    "date": "2019-10-27",
    "categories": [],
    "preview": {},
    "last_modified": "2019-10-27T17:50:57-03:00"
  },
  {
    "path": "posts/2019-10-16-modelos-multinomiales/",
    "title": "Modelos Multinomiales",
    "description": "A short description of the post.",
    "author": [
      {
        "name": "Gabriel Cabrera",
        "url": {}
      }
    ],
    "date": "2019-10-16",
    "categories": [],
    "preview": {},
    "last_modified": "2019-10-16T23:52:32-03:00"
  },
  {
    "path": "posts/2019-10-16-redes-neuronales/",
    "title": "Redes Neuronales",
    "description": "A short description of the post.",
    "author": [
      {
        "name": "Gabriel Cabrera",
        "url": {}
      }
    ],
    "date": "2019-10-16",
    "categories": [],
    "preview": {},
    "last_modified": "2019-10-16T23:54:20-03:00"
  },
  {
    "path": "posts/2019-10-16-svm/",
    "title": "Support Vector Machines",
    "description": "A short description of the post.",
    "author": [
      {
        "name": "Gabriel Cabrera",
        "url": {}
      }
    ],
    "date": "2019-10-16",
    "categories": [],
    "preview": {},
    "last_modified": "2019-10-16T23:54:52-03:00"
  },
  {
    "path": "posts/2019-09-10-logistica/",
    "title": "Regresión Logística",
    "description": "En construcción....",
    "author": [
      {
        "name": "Gabriel Cabrera",
        "url": {}
      }
    ],
    "date": "2019-09-10",
    "categories": [],
    "preview": "posts/2019-09-10-logistica/logistica_files/figure-html5/unnamed-chunk-2-1.png",
    "last_modified": "2019-09-19T17:12:00-03:00"
  },
  {
    "path": "posts/2019-09-10-polinomial/",
    "title": "Regresión Polinomial",
    "description": "En construcción....",
    "author": [
      {
        "name": "Gabriel Cabrera",
        "url": {}
      }
    ],
    "date": "2019-09-10",
    "categories": [],
    "preview": "posts/2019-09-10-polinomial/img/polinomial.png",
    "last_modified": "2019-09-20T22:59:59-03:00"
  },
  {
    "path": "posts/2019-09-10-regularizado/",
    "title": "Modelos Regularizados",
    "description": "En construcción....",
    "author": [
      {
        "name": "Gabriel Cabrera",
        "url": {}
      }
    ],
    "date": "2019-09-10",
    "categories": [],
    "preview": "posts/2019-09-10-regularizado/img/Regularization_web.png",
    "last_modified": "2019-09-19T11:13:46-03:00"
  },
  {
    "path": "posts/2019-09-01-trabajando-con-datos-financieros/",
    "title": "Trabajando con Datos Financieros",
    "description": "El post enseña como descargar datos financieros (índices accionarios), calcular retornos (acumulados) y graficarlos usando matplotlib. Otras funciones también son presentada.",
    "author": [
      {
        "name": "Gabriel Cabrera",
        "url": {}
      }
    ],
    "date": "2019-09-01",
    "categories": [],
    "preview": "posts/2019-09-01-trabajando-con-datos-financieros/img/finplot.png",
    "last_modified": "2019-09-20T22:42:54-03:00"
  },
  {
    "path": "posts/2019-08-26-pandas-avanzado/",
    "title": "Join & Merge en Pandas",
    "description": "El post continua con la librería pandas, introduciendo las capacidades que posee\npara unir y/o cruzar bases de datos.",
    "author": [
      {
        "name": "Gabriel Cabrera",
        "url": {}
      }
    ],
    "date": "2019-08-26",
    "categories": [],
    "preview": {},
    "last_modified": "2019-09-19T22:12:51-03:00"
  },
  {
    "path": "posts/2019-08-22-complejidad-computacional/",
    "title": "Complejidad Computacional",
    "description": "El post busca explicar el concepto de complejidad computacional utilizando como ejemplos el algorítmo de buscador lineal y la secuencia de fibonacci recursivo.",
    "author": [
      {
        "name": "Gabriel Cabrera",
        "url": {}
      }
    ],
    "date": "2019-08-22",
    "categories": [],
    "preview": "posts/2019-08-22-complejidad-computacional/img/complexity.png",
    "last_modified": "2019-10-20T22:48:36-03:00"
  },
  {
    "path": "posts/2019-08-22-gradiente-descendente/",
    "title": "Gradiente Descendiente",
    "description": "El post presenta el algorítmo de gradiente descendiente como una alternativa para encontrar la solución óptima a ciertos problemas en machine learning, sobre todo cuando se tiene muchos features en el modelo.",
    "author": [
      {
        "name": "Gabriel Cabrera",
        "url": {}
      }
    ],
    "date": "2019-08-22",
    "categories": [],
    "preview": "posts/2019-08-22-gradiente-descendente/img/predict_ols.png",
    "last_modified": "2019-10-17T00:14:45-03:00"
  },
  {
    "path": "posts/2019-08-10-elementos-basicos-de-python/",
    "title": "Elementos Básicos de Python",
    "description": "El post abarca los básico para trabajar con estructura de datos del tipo tuplas, \nlistas, diccionarios y conjuntos, a su vez construcción de loops (*comprehensions*) y funciones.",
    "author": [
      {
        "name": "Gabriel Cabrera",
        "url": {}
      }
    ],
    "date": "2019-08-10",
    "categories": [],
    "preview": {},
    "last_modified": "2019-08-21T22:19:31-04:00"
  },
  {
    "path": "posts/2019-08-10-introduccion-a-numpy/",
    "title": "Introduccion a Numpy",
    "description": "En construcción....",
    "author": [
      {
        "name": "Gabriel Cabrera",
        "url": {}
      }
    ],
    "date": "2019-08-10",
    "categories": [],
    "preview": {},
    "last_modified": "2019-09-19T22:12:13-03:00"
  },
  {
    "path": "posts/2019-08-10-introduccion-a-pandas/",
    "title": "Introducción a Pandas",
    "description": "El post introduce la librería Pandas para la construcción y manipulación de estructuras\nde datos basados en Series y DataFrame.",
    "author": [
      {
        "name": "Gabriel Cabrera",
        "url": {}
      }
    ],
    "date": "2019-08-10",
    "categories": [],
    "preview": {},
    "last_modified": "2019-09-19T22:12:37-03:00"
  },
  {
    "path": "posts/2019-08-10-regresion-lineal/",
    "title": "Regresión Lineal",
    "description": "En construcción.",
    "author": [
      {
        "name": "Gabriel Cabrera",
        "url": {}
      }
    ],
    "date": "2019-08-10",
    "categories": [],
    "preview": "posts/2019-08-10-regresion-lineal/regresion-lineal_files/figure-html5/unnamed-chunk-3-1.png",
    "last_modified": "2019-09-19T17:11:53-03:00"
  },
  {
    "path": "posts/2019-01-19-creating-a-local-server-using-python/",
    "title": "Setting Up a Web Server",
    "description": "Deploying a local server when some HTML restrictions exist.",
    "author": [
      {
        "name": "Gabriel Cabrera",
        "url": {}
      }
    ],
    "date": "2019-01-19",
    "categories": [],
    "preview": {},
    "last_modified": "2019-08-10T21:21:33-04:00"
  }
]
